{"stats":{"minecraft:killed":{"minecraft:cave_spider":1,"minecraft:shulker":1,"minecraft:skeleton":35,"irons_spellbooks:archevoker":1,"thermal:blitz":2,"minecraft:pillager":12,"irons_spellbooks:summoned_vex":3,"minecraft:zombie":83,"minecraft:cow":3,"minecraft:endermite":2,"eidolon:wraith":6,"minecraft:warden":1,"minecraft:husk":10,"endermanoverhaul:snowy_enderman":2,"irons_spellbooks:citadel_keeper":1,"minecraft:wandering_trader":2,"minecraft:enderman":1,"minecraft:witch":1,"creeperoverhaul:beach_creeper":2,"minecraft:spider":11,"minecraft:silverfish":1,"irons_spellbooks:summoned_skeleton":1,"minecraft:piglin_brute":5,"artifacts:mimic":1,"minecraft:piglin":15,"irons_spellbooks:necromancer":2,"minecraft:creeper":7,"minecraft:sheep":3,"minecraft:trader_llama":3,"minecraft:ghast":4,"eidolon:zombie_brute":3,"minecraft:blaze":27,"minecraft:vex":6,"irons_spellbooks:summoned_zombie":4,"minecraft:slime":6,"endermanoverhaul:soulsand_valley_enderman":2,"minecraft:wither_skeleton":4},"minecraft:killed_by":{"minecraft:vex":2,"minecraft:warden":1,"minecraft:wither_skeleton":1,"minecraft:player":2,"irons_spellbooks:archevoker":3},"minecraft:picked_up":{"minecraft:seagrass":5,"minecraft:iron_chestplate":1,"easy_villagers:breeder":1,"minecraft:chainmail_boots":1,"minecraft:creeper_head":2,"minecraft:flower_pot":2,"minecraft:prismarine_shard":5,"minecraft:lead":3,"minecraft:diamond_sword":1,"botania:black_double_flower":2,"gtceu:sticky_resin":16,"minecraft:oak_stairs":2,"minecraft:brewing_stand":2,"minecraft:golden_sword":2,"minecraft:amethyst_block":1,"minecraft:polished_deepslate":1,"forbidden_arcanus:xpetrified_orb":1,"minecraft:string":26,"minecraft:red_nether_bricks":2,"pipez:energy_pipe":1,"sushigocrafting:sesame_seeds":3,"minecraft:beetroot":4,"mysticalagriculture:inferium_essence":2320,"minecraft:cobbled_deepslate":264,"minecraft:spruce_planks":2,"minecraft:coal_block":5,"biomesoplenty:redwood_wood":64,"minecraft:melon_slice":18,"wstweaks:fragment":18,"minecraft:music_disc_blocks":1,"thermal:sadiroot_seeds":1,"potionsmaster:bezoar":2,"mysticalagriculture:prosperity_shard":861,"minecraft:acacia_log":2,"alltheores:raw_tin_block":14,"powah:player_transmitter_starter":1,"allthemodium:allthemodium_ingot":1,"evilcraft:box_of_eternal_closure":1,"quark:clear_shard":418,"biomesoplenty:rose_quartz_chunk":18,"aether:chainmail_gloves":2,"minecraft:iron_block":3,"minecraft:end_rod":1,"thermal:radish_seeds":1,"minecraft:white_terracotta":1,"ars_nouveau:sourceberry_bush":1,"mysticalagriculture:prudentium_essence":2,"supplementaries:ash":24,"minecraft:blaze_rod":52,"minecraft:snowball":4,"minecraft:birch_log":2,"minecraft:magma_block":1,"minecraft:feather":10,"minecraft:cooked_beef":4,"powah:dielectric_casing":2,"minecraft:iron_door":1,"minecraft:copper_block":6,"reliquary:molten_core":3,"minecraft:smoker":1,"minecraft:flint":66,"delightful:cantaloupe":1,"minecraft:lantern":4,"bhc:red_heart":11,"sushigocrafting:wasabi_seeds":2,"pipez:fluid_pipe":16,"delightful:mini_melon":4,"powah:capacitor_basic":3,"minecraft:dark_oak_sign":8,"minecraft:glowstone_dust":1,"minecraft:moss_block":1,"silentgear:fine_silk":2,"patchouli:guide_book":1,"irons_spellbooks:legendary_ink":1,"ae2:certus_quartz_crystal":4,"minecolonies:durum":1,"minecraft:trapped_chest":1,"minecraft:dark_oak_log":750,"minecraft:barrel":13,"quark:jasper":18,"minecraft:wither_skeleton_spawn_egg":1,"minecraft:bundle":2,"mininggadgets:mininggadget_simple":2,"ae2:chipped_budding_quartz":1,"allthemodium:raw_allthemodium":2,"minecraft:chainmail_helmet":1,"minecraft:bread":8,"reliquary:witch_hat":1,"twigs:rhyolite":6,"alltheores:raw_platinum":134,"ae2:silicon":11,"biomesoplenty:redwood_log":16,"minecraft:coarse_dirt":2,"minecraft:nether_wart":13,"minecraft:clay_ball":512,"minecraft:leather_leggings":1,"domum_ornamentum:architectscutter":1,"minecraft:dragon_head":1,"sushigocrafting:tobiko":2,"mcwfurnitures:dark_oak_bookshelf":1,"evilcraft:poison_sac":1,"pipez:advanced_upgrade":2,"minecraft:iron_shovel":1,"twigs:opaline_seashell":1,"supplementaries:bomb":5,"minecraft:cracked_stone_bricks":5,"minecraft:beef":5,"sushigocrafting:shrimp":1,"minecraft:iron_nugget":13,"minecraft:poppy":2,"ironfurnaces:diamond_furnace":1,"minecraft:chest":1,"minecraft:egg":2,"minecraft:stone":8,"reliquary:rib_bone":4,"alltheores:raw_zinc":65,"pipez:item_pipe":16,"minecraft:carrot":11,"minecraft:redstone":2233,"create:brass_casing":5,"ironjetpacks:jetpack":2,"irons_spellbooks:evocation_rune":2,"minecraft:tnt":3,"minecraft:beetroot_seeds":7,"ironfurnaces:gold_furnace":2,"minecraft:hay_block":29,"minecraft:deepslate_bricks":3,"minecraft:waxed_oxidized_cut_copper_stairs":2,"minecraft:cracked_deepslate_bricks":1,"tombstone:essence_of_undeath":1,"alltheores:raw_osmium":431,"minecraft:mutton":4,"minecraft:white_wool":3,"minecraft:rail":10,"powah:capacitor_basic_tiny":4,"croptopia:glowing_calamari":13,"minecraft:red_mushroom":2,"minecraft:oak_log":42,"minecraft:ancient_debris":29,"functionalstorage:storage_controller":1,"quark:limestone":13,"pipez:universal_pipe":16,"minecraft:spawner":11,"minecraft:apple":1,"minecraft:stone_bricks":39,"minecraft:kelp":14,"minecraft:stone_pickaxe":1,"ironfurnaces:augment_speed":2,"minecraft:cobweb":15,"tombstone:bag_of_seeds":5,"minecraft:iron_sword":2,"minecraft:dark_oak_stairs":2,"minecraft:polished_andesite_stairs":4,"thermal:blitz_rod":2,"minecraft:gravel":358,"twigs:bronzed_seashell":1,"powah:uraninite_raw":224,"silentgear:raw_azure_silver":11,"minecraft:leather_helmet":1,"biomesoplenty:flowering_oak_sapling":4,"minecraft:slime_ball":17,"immersiveengineering:seed":12,"minecraft:diamond_axe":1,"minecraft:gray_wool":8,"minecraft:hopper":2,"minecraft:ender_pearl":9,"irons_spellbooks:scroll":4,"minecraft:potion":1,"minecraft:stone_brick_stairs":4,"evilcraft:ender_tear":3,"minecraft:raw_copper":246,"bigreactors:anglesite_crystal":73,"minecraft:smooth_stone_slab":5,"minecraft:zombie_head":1,"minecraft:oak_sign":1,"irons_spellbooks:arcane_essence":11,"minecraft:deepslate_tiles":5,"reliquary:zombie_heart":3,"minecraft:bucket":3,"twigs:pebble":172,"delightful:acorn":2,"minecolonies:eggplant":1,"minecraft:rose_bush":1,"minecraft:ender_eye":29,"minecraft:calcite":2,"minecraft:wooden_shovel":1,"draconicevolution:draconium_dust":50,"minecraft:iron_pickaxe":1,"evilcraft:blood_extractor":2,"thermal:spinach_seeds":1,"ae2:flawed_budding_quartz":2,"minecraft:iron_boots":1,"minecraft:furnace":3,"minecraft:stick":5,"botania:lexicon":1,"apotheosis:gem":9,"minecraft:oak_fence":4,"minecraft:torch":62,"minecraft:spruce_stairs":2,"deeperdarker:heart_of_the_deep":2,"minecraft:porkchop":9,"tombstone:grave_dust":46,"thermal:flax_seeds":1,"ae2:sky_stone_block":134,"quark:ancient_tome":1,"eidolon:tattered_cloth":4,"minecraft:rotten_flesh":166,"allthemodium:allthemodium_upgrade_smithing_template":1,"ars_nouveau:whirlisprig_shards":1,"minecraft:chorus_flower":45,"reliquary:mob_charm_fragment":2,"evilcraft:condensed_blood":7,"minecraft:obsidian":229,"twigs:tangerine_seashell":1,"minecraft:blaze_powder":3,"minecraft:cobblestone":1586,"occultism:datura_seeds":5,"minecraft:lilac":1,"minecraft:andesite":1,"minecraft:golden_leggings":1,"minecraft:potato":16,"paraglider:spirit_orb":28,"minecraft:tuff":4,"supplementaries:flax_seeds":7,"refinedstorage:improved_processor":6,"ironfurnaces:upgrade_gold2":1,"ae2:damaged_budding_quartz":1,"minecraft:lapis_lazuli":92,"minecraft:dirt":79,"minecolonies:blockminecoloniesrack":2,"minecraft:glass":20,"alltheores:raw_tin":72,"minecraft:bone":100,"minecraft:bow":2,"minecraft:wheat_seeds":2,"minecraft:raw_gold":269,"minecraft:mossy_stone_bricks":9,"twigs:twig":10,"minecraft:oak_planks":28,"ironfurnaces:iron_furnace":3,"minecraft:ghast_tear":11,"thermal:bell_pepper_seeds":2,"minecraft:black_terracotta":2,"silentgear:pickaxe":2,"quark:shale":123,"alltheores:raw_lead":43,"torchmaster:megatorch":1,"evilcraft:dark_gem_crushed":55,"minecraft:sand":1089,"endermanoverhaul:soul_pearl":4,"ae2:quartz_block":5,"minecraft:orange_wool":103,"minecraft:dark_prismarine":3,"irons_spellbooks:blaze_spell_book":1,"forbidden_arcanus:ender_pearl_fragment":7,"minecraft:light_gray_terracotta":267,"minecraft:sugar":2,"minecraft:diamond":297,"minecraft:black_concrete":16,"waystones:waystone":1,"minecraft:cracked_polished_blackstone_bricks":1,"minecraft:crossbow":2,"minecraft:emerald":11,"minecraft:oak_sapling":6,"minecraft:netherrack":70,"minecraft:chorus_fruit":97,"minecraft:end_stone_bricks":8,"minecraft:blaze_spawn_egg":1,"minecraft:charcoal":17,"minecraft:allium":1,"minecraft:chicken":16,"evilcraft:dark_power_gem":3,"minecraft:brown_mushroom":1,"minecraft:stone_brick_wall":1,"minecraft:gold_block":10,"enderio:broken_spawner":12,"minecraft:shield":1,"minecraft:end_stone_brick_wall":9,"reliquary:chelicerae":2,"deeperdarker:warden_carapace":3,"minecraft:candle":1,"minecraft:sugar_cane":210,"reliquary:catalyzing_gland":1,"minecraft:end_stone":14382,"minecraft:raw_iron":492,"forbidden_arcanus:bat_wing":4,"minecraft:stripped_mangrove_wood":3,"dankstorage:dank_2":1,"minecraft:bowl":2,"mekanism:basic_energy_cube":1,"minecraft:trident":1,"powah:capacitor_basic_large":3,"minecraft:dark_oak_planks":1,"biomesoplenty:redwood_planks":1,"corn_delight:corn_seeds":1,"minecraft:weeping_vines":1,"minecraft:arrow":75,"alltheores:raw_osmium_block":4,"powah:wrench":1,"ae2:certus_quartz_dust":3,"powah:aerial_pearl":2,"artifacts:cross_necklace":1,"ironfurnaces:upgrade_diamond":1,"forbidden_arcanus:spawner_scrap":9,"minecraft:skeleton_skull":3,"minecraft:cracked_deepslate_tiles":1,"bhc:blue_heart":1,"integrateddynamics:drying_basin":1,"sushigocrafting:rice_seeds":1,"minecraft:glow_ink_sac":28,"minecraft:leather":10,"forbidden_arcanus:zombie_arm":1,"tombstone:villager_gift":1,"ironfurnaces:upgrade_gold":1,"minecraft:gunpowder":26,"powah:energy_cable_starter":6,"minecraft:cobblestone_wall":1,"botania:flower_bag":1,"ironfurnaces:upgrade_iron":1,"endermanoverhaul:icy_pearl":1,"draconicevolution:dragon_heart":1,"apotheosis:warden_tendril":1,"botania:black_mystical_flower":3,"caupona:fig_sapling":2,"minecraft:orange_terracotta":28,"alltheores:raw_zinc_block":7,"mekanism:salt":224,"minecraft:witch_spawn_egg":1,"minecraft:gray_carpet":1,"minecraft:iron_ingot":136,"minecraft:cooked_chicken":10,"comforts:sleeping_bag_gray":8,"refinedstorage:basic_processor":6,"irons_spellbooks:cinder_essence":1,"sophisticatedbackpacks:diamond_backpack":1,"minecraft:book":18,"quark:myalite":920,"minecraft:sculk_catalyst":1,"powah:binding_card_dim":1,"minecraft:stone_brick_slab":79,"minecraft:quartz":207,"minecraft:dandelion":3,"sushigocrafting:cucumber_seeds":3,"minecraft:lava_bucket":1,"refinedstorage:quartz_enriched_iron":5,"refinedstorage:machine_casing":1,"minecraft:amethyst_shard":20,"minecraft:white_bed":2,"irons_spellbooks:dragonskin":23,"botania:white_petal":3,"minecraft:spider_eye":18,"evilcraft:dark_tank":1,"thermal:rice_seeds":1,"mekanismgenerators:wind_generator":2,"minecraft:chainmail_leggings":1,"evilcraft:dark_gem":176,"tombstone:magic_scroll":8,"minecraft:terracotta":337,"naturesaura:aura_bloom":1,"minecraft:end_stone_brick_slab":18,"minecraft:coal":197},"minecraft:used":{"quark:shale":4,"minecraft:chest":1,"lootr:trophy":1,"minecraft:rotten_flesh":1,"fluxnetworks:flux_plug":1,"constructionwand:iron_wand":26,"refinedstorage:wireless_transmitter":1,"mekanism:basic_energy_cube":1,"refinedstorage:crafter_manager":1,"evilcraft:bucket_blood":5,"minecraft:copper_ore":18,"easy_villagers:iron_farm":9,"mcwfurnitures:dark_oak_bookshelf":2,"minecraft:stone_brick_stairs":1,"ironfurnaces:iron_furnace":6,"minecraft:dark_oak_boat":1,"minecraft:furnace":1,"mekanismgenerators:gas_burning_generator":1,"glassential:glass_ethereal":8,"creeperoverhaul:cave_creeper_spawn_egg":1,"minecraft:black_concrete_powder":16,"minecraft:enderman_spawn_egg":1,"mob_grinding_utils:ender_inhibitor_on":2,"sophisticatedstorage:basic_to_iron_tier_upgrade":1,"allthemodium:allthemodium_pickaxe":17529,"minecraft:diamond_sword":926,"allthemodium:allthemodium_ore":1,"minecraft:smithing_table":1,"ironfurnaces:gold_furnace":2,"minecraft:stone_sword":265,"minecraft:wither_skeleton_spawn_egg":1,"minecraft:netherrack":16,"minecraft:torch":30,"minecraft:brewing_stand":2,"minecraft:anvil":1,"botanypots:light_gray_terracotta_hopper_botany_pot":4,"ironfurnaces:diamond_furnace":1,"supplementaries:pedestal":1,"create:wrench":5,"minecraft:iron_axe":319,"minecraft:spawner":5,"minecraft:chicken_spawn_egg":3,"minecraft:barrel":16,"refinedstorageaddons:wireless_crafting_grid":3,"minecraft:blaze_spawn_egg":1,"silentgear:pickaxe":12,"constructionwand:diamond_wand":39,"minecraft:blaze_rod":1,"tombstone:gift":4,"torchmaster:megatorch":1,"minecraft:water_bucket":5,"integrateddynamics:drying_basin":2,"minecraft:cracked_stone_bricks":2,"refinedstorage:pattern_grid":1,"supplementaries:bomb":1,"minecraft:white_bed":1,"minecraft:oak_log":3,"quarryplus:workbench":1,"minecraft:ender_eye":47,"minecraft:diamond_pickaxe":1641,"minecraft:iron_pickaxe":1000,"refinedstorage:crafting_grid":1,"delightful:cantaloupe_slice":3,"minecraft:music_disc_blocks":1,"pipez:universal_pipe":4,"minecraft:potion":1,"minecraft:cobblestone":696,"evilcraft:dark_tank":3,"travelersbackpack:standard":1,"minecraft:brush":4,"create:redstone_link":6,"minecraft:iron_shovel":250,"minecraft:polished_deepslate":1,"easy_villagers:breeder":2,"refinedstorage:wrench":3,"minecraft:oak_sign":1,"minecraft:shield":49,"minecraft:iron_sword":1,"refinedstorage:crafting_monitor":1,"minecraft:carrot":2,"refinedstorage:controller":1,"minecraft:obsidian":17,"minecraft:glass":250,"sophisticatedbackpacks:diamond_backpack":1,"minecraft:lantern":5,"mekanismgenerators:wind_generator":4,"minecraft:stone_bricks":22,"mob_grinding_utils:entity_conveyor":52,"minecraft:hay_block":1,"pipez:item_pipe":19,"refinedstorage:disk_drive":1,"domum_ornamentum:architectscutter":1,"minecraft:witch_spawn_egg":1,"minecraft:stone_pickaxe":262,"minecraft:oak_planks":30,"minecraft:ender_pearl":2,"minecraft:sugar_cane":66,"botanypots:orange_terracotta_hopper_botany_pot":1,"sophisticatedstorage:basic_tier_upgrade":1,"glassential:glass_redstone":9,"enderio:dark_steel_sword":185,"mob_grinding_utils:saw":9,"waystones:waystone":1,"sophisticatedstorage:iron_to_gold_tier_upgrade":1,"minecraft:lever":1,"easy_villagers:villager":6,"mekanism:crusher":1,"minecraft:dark_oak_log":5,"minecraft:melon_slice":2,"mekanism:metallurgic_infuser":1,"utilitix:experience_crystal":2,"tombstone:grave_key":1,"minecraft:gravel":1,"croptopia:toast":151,"functionalstorage:oak_1":2,"cookingforblockheads:sink":1,"minecraft:flint_and_steel":2,"minecraft:redstone":1,"powah:player_transmitter_starter":3,"minecraft:cooked_chicken":9,"functionalstorage:configuration_tool":1,"evilcraft:purifier":1,"minecraft:dirt":3,"minecraft:hopper":3,"extrastorage:diamond_crafter":1,"functionalstorage:compacting_drawer":1,"minecraft:stone_brick_slab":760,"minecraft:netherite_pickaxe":1221,"mekanism:electrolytic_separator":1,"minecraft:cooked_beef":7,"mekanism:pressurized_reaction_chamber":1,"pipez:fluid_pipe":1,"minecraft:acacia_boat":1,"botanypots:terracotta_hopper_botany_pot":9,"fluxnetworks:flux_point":1,"minecraft:baked_potato":8,"evilcraft:blood_infuser":1,"powah:player_transmitter_basic":1,"mob_grinding_utils:ender_inhibitor_off":1,"minecolonies:supplychestdeployer":1,"minecraft:apple":1,"functionalstorage:oak_4":1,"minecraft:map":1,"comforts:sleeping_bag_gray":6,"minecraft:stone_axe":171,"allthemodium:teleport_pad":1,"minecraft:bucket":16,"pipez:energy_pipe":35,"minecraft:gray_wool":1,"minecraft:soul_torch":1},"minecraft:dropped":{"minecraft:diamond":10,"biomesoplenty:redwood_log":8,"ironjetpacks:jetpack":3,"irons_spellbooks:epic_ink":1,"minecraft:iron_pickaxe":1,"minecraft:bone":1,"mininggadgets:mininggadget_simple":3,"minecraft:stone_axe":1,"croptopia:toast":5,"minecraft:rotten_flesh":7,"minecraft:end_stone":64,"deeperdarker:heart_of_the_deep":1,"apotheosis:gem":1,"minecraft:stone_brick_stairs":1,"minecraft:enchanted_book":1,"apotheosis:potion_charm":1,"minecraft:feather":8,"minecraft:oak_stairs":2,"minecraft:string":1,"reliquary:rib_bone":1,"silentgear:pickaxe":2,"comforts:sleeping_bag_gray":3,"minecraft:ender_pearl":4,"minecraft:leather":5,"minecraft:cooked_mutton":4,"sophisticatedbackpacks:diamond_backpack":2,"minecraft:gunpowder":2,"minecraft:arrow":1,"gtceu:sticky_resin":8,"dankstorage:dank_2":2,"biomesoplenty:redwood_wood":60,"evilcraft:dark_gem":1,"irons_spellbooks:scroll":11,"minecraft:bucket":6,"powah:aerial_pearl":2,"powah:binding_card":1,"aether:chainmail_gloves":3,"powah:binding_card_dim":1,"refinedstorageaddons:wireless_crafting_grid":2},"minecraft:mined":{"mekanismgenerators:wind_generator":2,"minecraft:dragon_wall_head":1,"minecraft:white_bed":1,"mysticalagradditions:end_prosperity_ore":59,"minecraft:black_terracotta":2,"irons_spellbooks:armor_pile":1,"minecraft:red_nether_bricks":1,"minecraft:obsidian":236,"minecraft:acacia_log":2,"minecraft:stone_brick_wall":1,"minecraft:coal_block":1,"botania:black_double_flower":2,"supplementaries:blaze_rod":1,"minecraft:nether_wart":5,"mysticalagriculture:inferium_ore":27,"minecraft:spawner":31,"minecraft:chorus_flower":45,"minecraft:weeping_vines_plant":1,"minecraft:magma_block":1,"biomesoplenty:tall_lavender":2,"minecraft:cobbled_deepslate":1,"minecraft:barrel":12,"minecraft:deepslate_lapis_ore":7,"easy_villagers:breeder":1,"quark:limestone":11,"powah:uraninite_ore_poor":6,"ae2:large_quartz_bud":3,"minecraft:brown_mushroom":1,"pipez:energy_pipe":1,"minecraft:amethyst_cluster":1,"powah:uraninite_ore":18,"mekanism:block_salt":56,"ironfurnaces:iron_furnace":3,"bigreactors:anglesite_ore":21,"alltheores:raw_osmium_block":4,"mysticalagradditions:end_inferium_ore":86,"minecraft:polished_andesite_stairs":4,"minecraft:melon":3,"minecraft:dead_bush":1,"minecraft:glass":250,"mahoutsukai:mahoujin":1,"minecraft:sugar_cane":20,"botania:black_mystical_flower":3,"powah:deepslate_uraninite_ore_poor":11,"minecraft:amethyst_block":1,"mcwfurnitures:dark_oak_bookshelf":2,"alltheores:deepslate_osmium_ore":162,"alltheores:end_tin_ore":30,"alltheores:tin_ore":1,"minecraft:potted_poppy":1,"minecraft:stone_brick_stairs":3,"ae2:flawed_budding_quartz":1,"minecraft:grass":111,"delightful:mini_melon":4,"twigs:rhyolite":6,"domum_ornamentum:architectscutter":1,"silentgear:azure_silver_ore":3,"mysticalagriculture:deepslate_inferium_ore":86,"minecraft:deepslate":240,"powah:deepslate_uraninite_ore":9,"quark:shale":126,"alltheores:osmium_ore":59,"minecraft:dark_oak_log":814,"minecraft:end_stone":15562,"minecraft:redstone_wire":5,"minecraft:kelp":9,"minecraft:moss_block":1,"minecraft:red_mushroom":2,"minecraft:redstone_ore":9,"ae2:damaged_budding_quartz":4,"biomesoplenty:high_grass":1,"integrateddynamics:drying_basin":1,"alltheores:end_zinc_ore":2,"ae2:sky_stone_block":134,"biomesoplenty:rose_quartz_cluster":1,"minecraft:ender_chest":1,"alltheores:raw_zinc_block":7,"biomesoplenty:redwood_planks":1,"minecraft:chiseled_nether_bricks":1,"deeperdarker:ancient_vase":1,"minecraft:stone_brick_slab":80,"minecraft:dandelion":3,"biomesoplenty:high_grass_plant":1,"minecraft:copper_ore":27,"minecraft:tall_grass":4,"minecraft:deepslate_gold_ore":64,"alltheores:raw_tin_block":14,"minecraft:coarse_dirt":2,"ae2:flawless_budding_quartz":2,"minecraft:gravel":423,"minecraft:cobweb":1,"minecraft:stone_bricks":39,"minecraft:gold_ore":40,"alltheores:deepslate_zinc_ore":14,"minecraft:fern":6,"minecraft:large_amethyst_bud":2,"allthemodium:allthemodium_ore":2,"corn_delight:wild_corn":1,"minecraft:sculk_vein":5,"minecraft:end_stone_brick_wall":9,"minecraft:brewing_stand":2,"minecraft:grass_block":2,"ae2:quartz_cluster":1,"minecraft:cracked_polished_blackstone_bricks":1,"minecraft:purple_stained_glass_pane":3,"naturesaura:aura_bloom":1,"ironfurnaces:gold_furnace":1,"minecraft:iron_ore":119,"alltheores:deepslate_lead_ore":11,"minecraft:end_stone_bricks":8,"minecraft:deepslate_redstone_ore":303,"minecraft:blackstone":4,"minecraft:orange_terracotta":27,"minecraft:clay":128,"minecraft:light_gray_terracotta":267,"minecraft:end_stone_brick_slab":18,"minecraft:calcite":2,"create:brass_casing":5,"minecraft:nether_quartz_ore":63,"minecraft:cobblestone":40,"minecraft:oak_planks":15,"minecraft:iron_door":1,"evilcraft:dark_ore_deepslate":13,"delightful:cantaloupe":1,"minecraft:tnt":10,"minecraft:smooth_stone_slab":3,"ae2:quartz_block":1,"minecraft:oak_log":42,"minecraft:sand":1083,"minecraft:dirt":74,"mysticalagriculture:deepslate_prosperity_ore":8,"minecraft:netherrack":38,"ae2:chipped_budding_quartz":1,"alltheores:zinc_ore":4,"minecraft:deepslate_diamond_ore":67,"powah:deepslate_uraninite_ore_dense":4,"torchmaster:megatorch":1,"quark:jasper":18,"alltheores:deepslate_tin_ore":1,"minecraft:large_fern":8,"minecraft:hay_block":29,"minecraft:furnace":3,"minecraft:black_concrete":16,"evilcraft:dark_ore":14,"draconicevolution:end_draconium_ore":8,"minecraft:gold_block":10,"biomesoplenty:sea_oats":2,"minecraft:bookshelf":1,"alltheores:deepslate_platinum_ore":35,"minecraft:deepslate_iron_ore":42,"minecraft:lantern":2,"minecraft:chorus_plant":168,"minecraft:stone":1529,"minecraft:podzol":2,"quark:myalite":920,"minecraft:infested_stone_bricks":2,"minecraft:rose_bush":1,"minecraft:lapis_ore":3,"supplementaries:urn":16,"minecraft:gray_wool":1,"ironfurnaces:diamond_furnace":1,"forbidden_arcanus:xpetrified_ore":1,"minecraft:coal_ore":128,"minecraft:end_rod":1,"minecraft:cracked_stone_bricks":3,"minecraft:terracotta":337,"minecraft:mossy_stone_bricks":9,"biomesoplenty:redwood_wood":64},"minecraft:custom":{"minecraft:interact_with_crafting_table":19,"minecraft:open_barrel":187,"minecraft:bell_ring":13,"minecraft:eat_cake_slice":12,"minecraft:leave_game":3,"minecraft:time_since_death":32779,"minecraft:damage_blocked_by_shield":1128,"minecraft:play_time":1009448,"minecraft:deaths":11,"minecraft:jump":7764,"minecraft:interact_with_furnace":242,"minecraft:play_record":1,"minecraft:sleep_in_bed":11,"minecraft:waystone_activated":3,"tombstone:sneak_grave":2,"minecraft:damage_dealt":64419,"tombstone:undead_killed":148,"minecraft:interact_with_smoker":1,"minecraft:interact_with_smithing_table":9,"minecraft:interact_with_anvil":16,"minecraft:inspect_hopper":14,"minecraft:damage_dealt_absorbed":79,"minecraft:sneak_time":25415,"minecraft:interact_with_lectern":2,"minecraft:interact_with_blast_furnace":1,"minecraft:total_world_time":1009448,"tombstone:raider_killed":13,"minecraft:tune_noteblock":11,"minecraft:time_since_rest":1665,"minecraft:use_wand":712,"minecraft:swim_one_cm":59401,"minecraft:fly_one_cm":12266480,"minecraft:open_chest":636,"minecraft:fall_one_cm":326397,"lootr:looted_stat":148,"minecraft:open_shulker_box":5,"minecraft:damage_resisted":0,"minecraft:sprint_one_cm":1623545,"minecraft:drop":76,"minecraft:talked_to_villager":18,"minecraft:interact_with_brewingstand":12,"minecraft:walk_on_water_one_cm":65738,"minecraft:open_enderchest":1,"minecraft:player_kills":1,"minecraft:crouch_one_cm":131693,"tombstone:villager_killed":2,"minecraft:mob_kills":277,"minecraft:damage_dealt_resisted":164,"minecraft:climb_one_cm":18280,"minecraft:walk_one_cm":1736940,"minecraft:walk_under_water_one_cm":80808,"minecraft:boat_one_cm":630806,"minecraft:raid_trigger":1,"minecraft:damage_taken":16791},"minecraft:crafted":{"minecraft:lime_stained_glass":8,"minecraft:black_dye":14,"minecraft:blaze_powder":64,"botanypots:terracotta_hopper_botany_pot":1,"pipez:improved_upgrade":1,"sophisticatedbackpacks:magnet_upgrade":1,"mekanismtools:osmium_chestplate":1,"croptopia:toast":12,"minecraft:lever":1,"sophisticatedstorage:stack_upgrade_tier_1":1,"minecraft:cooked_mutton":4,"minecraft:iron_bars":32,"alltheores:brass_ingot":64,"minecraft:glass":166,"alltheores:osmium_dust":288,"refinedstorage:crafting_grid":3,"sophisticatedbackpacks:tank_upgrade":1,"evilcraft:blood_extractor":1,"allthemodium:allthemodium_pickaxe":1,"minecraft:melon_seeds":7,"refinedstorage:grid":3,"mekanismtools:osmium_boots":1,"refinedstorage:processor_binding":16,"glassential:glass_redstone":12,"ironfurnaces:upgrade_crystal":2,"allthemodium:allthemodium_nugget":1,"minecraft:gray_bed":1,"minecraft:flower_pot":6,"torchmaster:megatorch":1,"refinedstorage:raw_advanced_processor":9,"powah:blank_card":3,"minecraft:glass_bottle":3,"evilcraft:undead_planks":8,"allthemodium:allthemodium_upgrade_smithing_template":2,"minecraft:emerald":11,"silentgear:pickaxe_head":1,"silentgear:pickaxe_blueprint":1,"minecraft:smithing_table":1,"allthemodium:teleport_pad":1,"minecraft:copper_ingot":3,"minecraft:sticky_piston":1,"create:redstone_link":6,"minecraft:blaze_rod":1,"allthemodium:allthemodium_dust":4,"potionsmaster:netherite_powder":1,"comforts:sleeping_bag_gray":2,"minecraft:iron_pickaxe":4,"minecraft:iron_block":41,"minecraft:gold_ingot":50,"minecraft:netherite_ingot":1,"refinedstorage:machine_casing":5,"powah:capacitor_basic_tiny":2,"silentgear:pickaxe":5,"powah:dielectric_casing":5,"mob_grinding_utils:ender_inhibitor_on":2,"refinedstorage:upgrade":1,"sophisticatedstorage:basic_tier_upgrade":2,"minecraft:iron_nugget":9,"mysticalagriculture:inferium_farmland":5,"sophisticatedbackpacks:stack_upgrade_tier_1":1,"ironjetpacks:basic_coil":66,"easy_villagers:iron_farm":9,"minecraft:bone_meal":8,"evilcraft:dark_block":1,"botania:black_petal":6,"alltheores:copper_ore_hammer":9,"minecraft:diamond":4,"sophisticatedbackpacks:advanced_void_upgrade":1,"sophisticatedstorage:upgrade_base":1,"minecraft:black_concrete_powder":16,"ironjetpacks:strap":2,"minecraft:ender_pearl":14,"minecraft:stone_pickaxe":1,"mob_grinding_utils:mob_swab":4,"minecraft:redstone_block":65,"minecraft:dark_oak_planks":77,"ironjetpacks:thruster":24,"minecraft:wheat":36,"powah:dielectric_paste":24,"constructionwand:diamond_wand":1,"minecraft:netherite_pickaxe":1,"potionsmaster:ender_powder":1,"evilcraft:dark_tank":1,"biomesoplenty:redwood_planks":24,"functionalstorage:oak_4":4,"ironjetpacks:advanced_coil":44,"refinedstorage:wireless_transmitter":1,"ironfurnaces:upgrade_obsidian2":2,"sophisticatedbackpacks:gold_backpack":3,"refinedstorage:raw_improved_processor":1,"mob_grinding_utils:saw":9,"evilcraft:purifier":1,"ironjetpacks:cell":60,"minecraft:cobblestone":40,"refinedstorage:raw_basic_processor":6,"evilcraft:blood_infuser":1,"powah:capacitor_basic":4,"ironfurnaces:upgrade_diamond":2,"utilitix:experience_crystal":2,"minecraft:farmland":6,"delightful:cantaloupe_slice":1,"minecraft:oak_planks":80,"minecraft:barrel":4,"botanypots:light_gray_terracotta_hopper_botany_pot":4,"minecraft:dark_oak_boat":1,"minecraft:melon_slice":4,"alltheores:copper_dust":44,"alltheores:iron_ore_hammer":1,"refinedstorage:controller":1,"minecolonies:supplycampdeployer":1,"sophisticatedbackpacks:void_upgrade":1,"minecraft:green_dye":3,"minecraft:hopper":6,"minecraft:stone_brick_slab":555,"evilcraft:promise_tier_1":1,"minecraft:comparator":5,"minecraft:dead_bush":1,"functionalstorage:gold_upgrade":1,"minecraft:chest":30,"minecraft:copper_block":19,"minecraft:netherite_upgrade_smithing_template":6,"refinedstorage:disk_drive":1,"minecraft:ender_eye":97,"minecraft:stone_bricks":101,"minecraft:oak_slab":36,"sophisticatedbackpacks:backpack":2,"ironjetpacks:jetpack":12,"mob_grinding_utils:gm_chicken_feed":3,"mob_grinding_utils:entity_conveyor":54,"minecraft:crafting_table":5,"constructionwand:iron_wand":1,"minecraft:brush":1,"minecraft:gold_block":15,"evilcraft:bowl_of_promises_empty":1,"mekanismtools:osmium_leggings":1,"sophisticatedbackpacks:upgrade_base":3,"silentgear:blueprint_paper":4,"ironjetpacks:capacitor":12,"minecraft:diamond_pickaxe":1,"minecraft:yellow_dye":3,"sophisticatedbackpacks:diamond_backpack":3,"minecraft:stick":392,"minecraft:iron_ingot":10,"minecraft:stone_sword":2,"evilcraft:vein_sword":1,"minecraft:redstone_torch":24,"quarryplus:workbench":1,"evilcraft:vengeance_pickaxe":3,"refinedstorage:pattern":2,"pipez:advanced_upgrade":1,"evilcraft:dark_spike":16,"minecraft:coal":11,"evilcraft:bowl_of_promises_dusted":1,"alltheores:raw_osmium":4,"glassential:glass_ethereal":8,"sophisticatedbackpacks:advanced_magnet_upgrade":1,"minecraft:furnace":27,"alltheores:gold_dust":270,"minecraft:piston":4,"refinedstorage:wrench":1,"refinedstorage:quartz_enriched_iron":43,"minecraft:diamond_block":1,"minecraft:glass_pane":80,"minecraft:flint_and_steel":1,"refinedstorage:destruction_core":3,"apotheosis:potion_charm":1,"minecraft:iron_axe":2,"minecraft:iron_hoe":1,"minecraft:lime_dye":3,"evilcraft:dark_stick":8,"powah:player_transmitter_starter":3,"sophisticatedbackpacks:stack_upgrade_tier_2":1,"mekanismtools:osmium_helmet":1,"powah:dielectric_rod_horizontal":16,"sophisticatedbackpacks:iron_backpack":3,"mekanism:metallurgic_infuser":1,"evilcraft:blood_infusion_core":2,"minecraft:iron_sword":72,"mob_grinding_utils:spikes":18,"sophisticatedstorage:iron_to_gold_tier_upgrade":2,"integrateddynamics:drying_basin":1,"ironjetpacks:elite_coil":22,"refinedstorage:range_upgrade":1,"sophisticatedstorage:basic_to_iron_tier_upgrade":2,"minecraft:bucket":2,"crafting_on_a_stick:crafting_table":2,"minecraft:stone_axe":2,"mekanism:upgrade_speed":35,"minecraft:acacia_boat":1,"minecraft:bread":84,"minecraft:air":3705,"refinedstorageaddons:wireless_crafting_grid":3,"minecraft:blue_dye":8,"powah:dielectric_rod":16,"sophisticatedbackpacks:pickup_upgrade":1,"mysticalagriculture:prudentium_farmland":1,"powah:player_transmitter_basic":1,"functionalstorage:copper_upgrade":1,"powah:aerial_pearl":3,"minecraft:white_dye":3,"minecraft:raw_gold":22,"powah:binding_card":3,"mekanism:upgrade_energy":29,"botanypots:orange_terracotta_hopper_botany_pot":1,"easy_villagers:breeder":1,"refinedstorage:construction_core":3,"minecraft:anvil":1,"alltheores:iron_dust":70,"minecraft:acacia_planks":8,"sophisticatedstorage:stack_upgrade_tier_2":1,"minecraft:torch":4,"absentbydesign:slab_wool_white":1},"minecraft:broken":{"mekanismtools:osmium_helmet":1,"mekanismtools:osmium_boots":1,"minecraft:stone_sword":2,"aether:iron_gloves":1,"minecraft:iron_axe":1,"minecraft:iron_pickaxe":4,"minecraft:iron_shovel":1,"minecraft:stone_pickaxe":2,"constructionwand:iron_wand":1,"aether:chainmail_gloves":1}},"DataVersion":3465}